rlython-0.1.0.dist-info/licenses/LICENSE
rython/__init__.py
rython/basic_traits.py
rython/iterators.py
rython/monads.py
rlython-0.1.0.dist-info/METADATA
rlython-0.1.0.dist-info/WHEEL
rlython-0.1.0.dist-info/top_level.txt
rlython-0.1.0.dist-info/RECORD
