Metadata-Version: 2.4
Name: rlython
Version: 0.1.0
Summary: Rust-like traits and patterns for Python
Requires-Python: >=3.10
License-File: LICENSE
Provides-Extra: dev
Requires-Dist: pytest; extra == "dev"
Requires-Dist: pytest-cov; extra == "dev"
Requires-Dist: ruff; extra == "dev"
Requires-Dist: pyrefly; extra == "dev"
Requires-Dist: ty; extra == "dev"
Dynamic: license-file
